Metadata-Version: 1.1
Name: djangocms-renderit-plugin
Version: 0.2.1
Summary: Use Django templating language in DjangoCMS plugins.
Home-page: https://github.com/frnhr/djangocms_renderit
Author: frnhr
Author-email: frnhr@changeset.hr
License: UNKNOWN
Download-URL: https://github.com/frnhr/djangocms_renderit/tarball/0.1
Keywords: djangocms,django-template
Platform: UNKNOWN
